README.md
setup.py
tptsam/__init__.py
tptsam.egg-info/PKG-INFO
tptsam.egg-info/SOURCES.txt
tptsam.egg-info/dependency_links.txt
tptsam.egg-info/not-zip-safe
tptsam.egg-info/top_level.txt