Metadata-Version: 1.0
Name: tptsam
Version: 0.1
Summary: InsertDescription
Home-page: https://github.com/samuelsonsev/tptsam
Author: Samuelson Esteves Vieira
Author-email: none@example.com
License: MIT
Platform: UNKNOWN
